README.md
setup.py
googlesearchpy/__init__.py
googlesearchpy/googlesearch.py
googlesearchpy/utils.py
googlesearchpy.egg-info/PKG-INFO
googlesearchpy.egg-info/SOURCES.txt
googlesearchpy.egg-info/dependency_links.txt
googlesearchpy.egg-info/top_level.txt