Metadata-Version: 1.0
Name: googlesearchpy
Version: 1.0.0
Summary: A wrapper for the Google Search API
Home-page: UNKNOWN
Author: Matt Eads
Author-email: matteads2@gmail.com
License: UNKNOWN
Project-URL: Source Code, https://github.com/meads2/googlesearch
Keywords: google web scraping parse
Platform: UNKNOWN
